[
	{
		"word": "布娃娃",
		"tip": "儿童玩具"
	},
	{
		"word": "激光",
		"tip": "光学武器"
	},
	{
		"word": "餐巾纸",
		"tip": "餐具"
	},
	{
		"word": "大脖子病",
		"tip": "一种病症"
	},
	{
		"word": "仓库",
		"tip": "建筑类"
	},
	{
		"word": "丁字裤",
		"tip": "一种内衣"
	},
	{
		"word": "CD",
		"tip": "一种数据存储"
	},
	{
		"word": "蜂蜜",
		"tip": "食品类"
	},
	{
		"word": "瓷器",
		"tip": "容器类"
	},
	{
		"word": "人民币",
		"tip": "货币类"
	},
	{
		"word": "三峡大坝",
		"tip": "水利类"
	},
	{
		"word": "手纸",
		"tip": "日用品"
	},
	{
		"word": "沙漏",
		"tip": "计时器类"
	},
	{
		"word": "雷人",
		"tip": "网络语"
	},
	{
		"word": "除草剂",
		"tip": "清除作用的药物"
	},
	{
		"word": "淘宝",
		"tip": "电商"
	},
	{
		"word": "不入虎穴焉得虎子",
		"tip": "俗语"
	},
	{
		"word": "原子弹",
		"tip": "武器类"
	},
	{
		"word": "树苗",
		"tip": "植物类"
	},
	{
		"word": "娃哈哈",
		"tip": "儿童饮料"
	},
	{
		"word": "大头鱼",
		"tip": "水产类"
	},
	{
		"word": "仙人掌",
		"tip": "植物"
	},
	{
		"word": "手术刀",
		"tip": "医疗器械"
	},
	{
		"word": "疯子",
		"tip": "非正常人类"
	},
	{
		"word": "豆沙包",
		"tip": "食品"
	},
	{
		"word": "城管",
		"tip": "一种现代职业"
	},
	{
		"word": "射雕英雄传",
		"tip": "古代小说"
	},
	{
		"word": "凤姐",
		"tip": "网络名人"
	},
	{
		"word": "耳机",
		"tip": "电子产品"
	},
	{
		"word": "钓鱼岛",
		"tip": "中国固有领土"
	},
	{
		"word": "飞碟",
		"tip": "交通工具"
	},
	{
		"word": "靖国神社",
		"tip": "被称为岛国神侧"
	},
	{
		"word": "工资",
		"tip": "劳动所得"
	},
	{
		"word": "口吃",
		"tip": "病症"
	},
	{
		"word": "蟾蜍",
		"tip": "益虫"
	},
	{
		"word": "冰雹",
		"tip": "天气术语"
	},
	{
		"word": "落井下石",
		"tip": "一种行为"
	},
	{
		"word": "僵尸",
		"tip": "神话人物"
	},
	{
		"word": "游泳衣",
		"tip": "服装类"
	},
	{
		"word": "齐白石",
		"tip": "艺术家名字"
	},
	{
		"word": "呲牙咧嘴",
		"tip": "一种表情"
	},
	{
		"word": "打火机",
		"tip": "日用品"
	},
	{
		"word": "酒鬼",
		"tip": "形容一个人的嗜好"
	},
	{
		"word": "同流合污",
		"tip": "成语"
	},
	{
		"word": "外星人",
		"tip": "一种生物"
	},
	{
		"word": "山楂",
		"tip": "水果"
	},
	{
		"word": "山药",
		"tip": "蔬菜类"
	},
	{
		"word": "牛奶",
		"tip": "饮品"
	},
	{
		"word": "蹦极",
		"tip": "体育运动"
	},
	{
		"word": "寻花问柳",
		"tip": "成语"
	},
	{
		"word": "死不瞑目",
		"tip": "一种表情"
	},
	{
		"word": "色迷迷",
		"tip": "形容一种表情"
	},
	{
		"word": "哈喇子",
		"tip": "人体类"
	},
	{
		"word": "钓鱼",
		"tip": "一种运动"
	},
	{
		"word": "花仙子",
		"tip": "神话人物"
	},
	{
		"word": "兔女郎",
		"tip": "一种角色"
	},
	{
		"word": "董存瑞",
		"tip": "历史人物"
	},
	{
		"word": "日环食",
		"tip": "天文现象"
	},
	{
		"word": "击剑",
		"tip": "体育比赛"
	},
	{
		"word": "盗墓",
		"tip": "一种非法行为"
	},
	{
		"word": "花前月下",
		"tip": "一种场景"
	},
	{
		"word": "春梦",
		"tip": "一种生理现象"
	},
	{
		"word": "监狱",
		"tip": "一种场合"
	},
	{
		"word": "贞子",
		"tip": "神话人物"
	},
	{
		"word": "结婚证",
		"tip": "一种证件"
	},
	{
		"word": "入洞房",
		"tip": "人生乐事之一"
	},
	{
		"word": "空格键",
		"tip": "电子部件"
	},
	{
		"word": "别墅",
		"tip": "建筑类"
	},
	{
		"word": "KTV",
		"tip": "一 种场合"
	},
	{
		"word": "人造卫星",
		"tip": "人造天体"
	},
	{
		"word": "刘翔",
		"tip": "人名"
	},
	{
		"word": "WC",
		"tip": "一种场所"
	},
	{
		"word": "挖鼻屎",
		"tip": "一种行为"
	},
	{
		"word": "草泥马",
		"tip": "一种动物"
	},
	{
		"word": "奶牛",
		"tip": "动物类"
	},
	{
		"word": "帅哥",
		"tip": "一种美称"
	},
	{
		"word": "插排",
		"tip": "家用电器"
	},
	{
		"word": "癞蛤蟆",
		"tip": "一种益虫"
	},
	{
		"word": "秦始皇兵马俑",
		"tip": "文物古迹"
	},
	{
		"word": "司马光",
		"tip": "古代小英雄"
	},
	{
		"word": "汉堡",
		"tip": "食品"
	},
	{
		"word": "眼镜框",
		"tip": "饰品"
	},
	{
		"word": "沙僧",
		"tip": "神话人物"
	},
	{
		"word": "洲际导弹",
		"tip": "远程武器"
	},
	{
		"word": "圣经",
		"tip": "书籍类"
	},
	{
		"word": "孟婆汤",
		"tip": "一种消除记忆的饮料"
	},
	{
		"word": "升旗",
		"tip": "行为类"
	},
	{
		"word": "灰太狼",
		"tip": "动画人物"
	},
	{
		"word": "钻戒",
		"tip": "首饰类"
	},
	{
		"word": "米老鼠",
		"tip": "动画人物"
	},
	{
		"word": "天文望远镜",
		"tip": "一种光学仪器"
	},
	{
		"word": "水漫金山",
		"tip": "神话故事"
	},
	{
		"word": "瞎猫遇见死老鼠",
		"tip": "俗语"
	},
	{
		"word": "五马分尸",
		"tip": "古代刑罚"
	}
]
